cached_conv/__init__.py
cached_conv/convs.py
cached_conv/test_align_branches.py
cached_conv/test_conv.py
cached_conv/test_conv_t.py
cached_conv/test_script.py
cached_conv/test_sequential.py
cached_conv-2.5.0.dist-info/LICENSE
cached_conv-2.5.0.dist-info/METADATA
cached_conv-2.5.0.dist-info/WHEEL
cached_conv-2.5.0.dist-info/top_level.txt
cached_conv-2.5.0.dist-info/RECORD
