Metadata-Version: 2.1
Name: cached_conv
Version: 2.5.0
Summary: Tools allowing to use neural network inside realtime apps.
Author: Antoine CAILLON
Author-email: caillon@ircam.fr
Classifier: Programming Language :: Python :: 3
Classifier: License :: OSI Approved :: MIT License
Classifier: Operating System :: OS Independent
Requires-Python: >=3.7
License-File: LICENSE
